{
    "gameType": "tenseMastery",
    "batchIndex": 5,
    "levels": "41-50",
    "quests": [
        {
            "id": "GRM_TENSEMASTERY_L41_Q1",
            "interactionType": "Tense Slider",
            "hint": "Pay attention to the action to choose the right answer.",
            "explanation": "Understanding sentence structure improves fluency.",
            "sentence": "The detective creates a spaceship efficiently.",
            "correctAnswer": "A scientist activates a spaceship efficiently."
        },
        {
            "id": "GRM_TENSEMASTERY_L41_Q2",
            "interactionType": "Tense Slider",
            "hint": "Look at who receives the action to understand the context.",
            "explanation": "Practicing grammar rules enhances writing skills.",
            "sentence": "A spy creates a spaceship efficiently.",
            "correctAnswer": "The commander activates a spaceship efficiently."
        },
        {
            "id": "GRM_TENSEMASTERY_L41_Q3",
            "interactionType": "Tense Slider",
            "hint": "Examine the sentence structure to switch voices.",
            "explanation": "Learning verb forms strengthens flexibility.",
            "sentence": "The driver creates a spaceship efficiently.",
            "correctAnswer": "A pilot activates a spaceship efficiently."
        },
        {
            "id": "GRM_TENSEMASTERY_L42_Q1",
            "interactionType": "Tense Slider",
            "hint": "Look at who receives the action to find the correct form.",
            "explanation": "Practicing active and passive voice builds sentence variety.",
            "sentence": "A student evaluates the portal accurately.",
            "correctAnswer": "The traveler evaluates the portal accurately."
        },
        {
            "id": "GRM_TENSEMASTERY_L42_Q2",
            "interactionType": "Tense Slider",
            "hint": "Examine the sentence structure to choose the right answer.",
            "explanation": "Learning sentence structure improves fluency.",
            "sentence": "The analyst evaluates the portal accurately.",
            "correctAnswer": "A doctor evaluates the portal accurately."
        },
        {
            "id": "GRM_TENSEMASTERY_L42_Q3",
            "interactionType": "Tense Slider",
            "hint": "Check the subject to understand the context.",
            "explanation": "Recognizing grammar rules enhances writing skills.",
            "sentence": "A manager evaluates the portal accurately.",
            "correctAnswer": "The teacher evaluates the portal accurately."
        },
        {
            "id": "GRM_TENSEMASTERY_L43_Q1",
            "interactionType": "Tense Slider",
            "hint": "Examine the sentence structure to switch voices.",
            "explanation": "Learning verb forms strengthens flexibility.",
            "sentence": "The driver analyzes the circuit steadily.",
            "correctAnswer": "A pilot creates the circuit steadily."
        },
        {
            "id": "GRM_TENSEMASTERY_L43_Q2",
            "interactionType": "Tense Slider",
            "hint": "Check the subject to find the correct form.",
            "explanation": "Recognizing active and passive voice builds sentence variety.",
            "sentence": "A chef analyzes the circuit steadily.",
            "correctAnswer": "The technician creates the circuit steadily."
        },
        {
            "id": "GRM_TENSEMASTERY_L43_Q3",
            "interactionType": "Tense Slider",
            "hint": "Focus on the verb to choose the right answer.",
            "explanation": "Mastering sentence structure improves fluency.",
            "sentence": "The engineer creates the circuit steadily.",
            "correctAnswer": "An explorer creates the circuit steadily."
        },
        {
            "id": "GRM_TENSEMASTERY_L44_Q1",
            "interactionType": "Tense Slider",
            "hint": "Check the subject to understand the context.",
            "explanation": "Recognizing grammar rules enhances writing skills.",
            "sentence": "A manager navigates the network flawlessly.",
            "correctAnswer": "The teacher navigates the network flawlessly."
        },
        {
            "id": "GRM_TENSEMASTERY_L44_Q2",
            "interactionType": "Tense Slider",
            "hint": "Focus on the verb to switch voices.",
            "explanation": "Mastering verb forms strengthens flexibility.",
            "sentence": "The hero navigates the network flawlessly.",
            "correctAnswer": "A researcher navigates the network flawlessly."
        },
        {
            "id": "GRM_TENSEMASTERY_L44_Q3",
            "interactionType": "Tense Slider",
            "hint": "Pay attention to the action to find the correct form.",
            "explanation": "Understanding active and passive voice builds sentence variety.",
            "sentence": "A robot navigates the network flawlessly.",
            "correctAnswer": "The detective navigates the network flawlessly."
        },
        {
            "id": "GRM_TENSEMASTERY_L45_Q1",
            "interactionType": "Tense Slider",
            "hint": "Focus on the verb to choose the right answer.",
            "explanation": "Mastering sentence structure improves fluency.",
            "sentence": "The engineer analyzes the database boldly.",
            "correctAnswer": "An explorer analyzes the database boldly."
        },
        {
            "id": "GRM_TENSEMASTERY_L45_Q2",
            "interactionType": "Tense Slider",
            "hint": "Pay attention to the action to understand the context.",
            "explanation": "Understanding grammar rules enhances writing skills.",
            "sentence": "A scientist analyzes the database boldly.",
            "correctAnswer": "The droid analyzes the database boldly."
        },
        {
            "id": "GRM_TENSEMASTERY_L45_Q3",
            "interactionType": "Tense Slider",
            "hint": "Look at who receives the action to switch voices.",
            "explanation": "Practicing verb forms strengthens flexibility.",
            "sentence": "The commander analyzes the database boldly.",
            "correctAnswer": "A student analyzes the database boldly."
        },
        {
            "id": "GRM_TENSEMASTERY_L46_Q1",
            "interactionType": "Tense Slider",
            "hint": "Pay attention to the action to find the correct form.",
            "explanation": "Understanding active and passive voice builds sentence variety.",
            "sentence": "A robot operates a reactor carefully.",
            "correctAnswer": "The detective operates a reactor carefully."
        },
        {
            "id": "GRM_TENSEMASTERY_L46_Q2",
            "interactionType": "Tense Slider",
            "hint": "Look at who receives the action to choose the right answer.",
            "explanation": "Practicing sentence structure improves fluency.",
            "sentence": "The traveler operates a reactor carefully.",
            "correctAnswer": "A spy operates a reactor carefully."
        },
        {
            "id": "GRM_TENSEMASTERY_L46_Q3",
            "interactionType": "Tense Slider",
            "hint": "Examine the sentence structure to understand the context.",
            "explanation": "Learning grammar rules enhances writing skills.",
            "sentence": "A doctor operates a reactor carefully.",
            "correctAnswer": "The driver operates a reactor carefully."
        },
        {
            "id": "GRM_TENSEMASTERY_L47_Q1",
            "interactionType": "Tense Slider",
            "hint": "Look at who receives the action to switch voices.",
            "explanation": "Practicing verb forms strengthens flexibility.",
            "sentence": "The commander repairs a laser successfully.",
            "correctAnswer": "A student repairs a laser successfully."
        },
        {
            "id": "GRM_TENSEMASTERY_L47_Q2",
            "interactionType": "Tense Slider",
            "hint": "Examine the sentence structure to find the correct form.",
            "explanation": "Learning active and passive voice builds sentence variety.",
            "sentence": "A pilot repairs a laser successfully.",
            "correctAnswer": "The analyst repairs a laser successfully."
        },
        {
            "id": "GRM_TENSEMASTERY_L47_Q3",
            "interactionType": "Tense Slider",
            "hint": "Check the subject to choose the right answer.",
            "explanation": "Recognizing sentence structure improves fluency.",
            "sentence": "The technician repairs a laser successfully.",
            "correctAnswer": "A manager repairs a laser successfully."
        },
        {
            "id": "GRM_TENSEMASTERY_L48_Q1",
            "interactionType": "Tense Slider",
            "hint": "Examine the sentence structure to understand the context.",
            "explanation": "Learning grammar rules enhances writing skills.",
            "sentence": "A doctor investigates the software perfectly.",
            "correctAnswer": "The driver investigates the software perfectly."
        },
        {
            "id": "GRM_TENSEMASTERY_L48_Q2",
            "interactionType": "Tense Slider",
            "hint": "Check the subject to switch voices.",
            "explanation": "Recognizing verb forms strengthens flexibility.",
            "sentence": "The teacher investigates the software perfectly.",
            "correctAnswer": "A chef investigates the software perfectly."
        },
        {
            "id": "GRM_TENSEMASTERY_L48_Q3",
            "interactionType": "Tense Slider",
            "hint": "Focus on the verb to find the correct form.",
            "explanation": "Mastering active and passive voice builds sentence variety.",
            "sentence": "A researcher investigates the software perfectly.",
            "correctAnswer": "The engineer operates the software perfectly."
        },
        {
            "id": "GRM_TENSEMASTERY_L49_Q1",
            "interactionType": "Tense Slider",
            "hint": "Check the subject to choose the right answer.",
            "explanation": "Recognizing sentence structure improves fluency.",
            "sentence": "The technician monitors the archive smoothly.",
            "correctAnswer": "A manager monitors the archive smoothly."
        },
        {
            "id": "GRM_TENSEMASTERY_L49_Q2",
            "interactionType": "Tense Slider",
            "hint": "Focus on the verb to understand the context.",
            "explanation": "Mastering grammar rules enhances writing skills.",
            "sentence": "An explorer monitors the archive smoothly.",
            "correctAnswer": "The hero monitors the archive smoothly."
        },
        {
            "id": "GRM_TENSEMASTERY_L49_Q3",
            "interactionType": "Tense Slider",
            "hint": "Pay attention to the action to switch voices.",
            "explanation": "Understanding verb forms strengthens flexibility.",
            "sentence": "The droid monitors the archive smoothly.",
            "correctAnswer": "A robot monitors the archive smoothly."
        },
        {
            "id": "GRM_TENSEMASTERY_L50_Q1",
            "interactionType": "Tense Slider",
            "hint": "Pay attention to the action to switch voices.",
            "explanation": "Understanding verb forms strengthens flexibility.",
            "sentence": "The droid investigates the portal swiftly.",
            "correctAnswer": "A robot investigates the portal swiftly."
        },
        {
            "id": "GRM_TENSEMASTERY_L50_Q2",
            "interactionType": "Tense Slider",
            "hint": "Look at who receives the action to find the correct form.",
            "explanation": "Practicing active and passive voice builds sentence variety.",
            "sentence": "A student investigates the portal swiftly.",
            "correctAnswer": "The traveler investigates the portal swiftly."
        },
        {
            "id": "GRM_TENSEMASTERY_L50_Q3",
            "interactionType": "Tense Slider",
            "hint": "Examine the sentence structure to choose the right answer.",
            "explanation": "Learning sentence structure improves fluency.",
            "sentence": "The analyst investigates the portal swiftly.",
            "correctAnswer": "A doctor investigates the portal swiftly."
        }
    ]
}