{
    "gameType":  "fastSpeechDecoder",
    "batchIndex":  3,
    "levels":  "21-30",
    "quests":  [
                   {
                       "id":  "LIS_FASTSPEECHDECODER_L21_Q1",
                       "interactionType":  "Speed Dial",
                       "xp":  10,
                       "coins":  10,
                       "hint":  "Focus on \u0027Whatcha\u0027 and \u0027gonna\u0027.",
                       "explanation":  "Decoding fast speech improves real-world fluency.",
                       "textToSpeak":  "Whatcha gonna do about it?",
                       "options":  [
                                       "What are you going to do about it?",
                                       "What you doing about it?",
                                       "Where you going about it?"
                                   ],
                       "correctAnswerIndex":  0
                   },
                   {
                       "id":  "LIS_FASTSPEECHDECODER_L21_Q2",
                       "interactionType":  "Speed Dial",
                       "xp":  10,
                       "coins":  10,
                       "hint":  "Focus on \u0027Whatcha\u0027 and \u0027gonna\u0027.",
                       "explanation":  "Decoding fast speech improves real-world fluency.",
                       "textToSpeak":  "Whatcha gonna do about it?",
                       "options":  [
                                       "What are you going to do about it?",
                                       "What you doing about it?",
                                       "Where you going about it?"
                                   ],
                       "correctAnswerIndex":  0
                   },
                   {
                       "id":  "LIS_FASTSPEECHDECODER_L21_Q3",
                       "interactionType":  "Speed Dial",
                       "xp":  10,
                       "coins":  10,
                       "hint":  "Focus on \u0027Whatcha\u0027 and \u0027gonna\u0027.",
                       "explanation":  "Decoding fast speech improves real-world fluency.",
                       "textToSpeak":  "Whatcha gonna do about it?",
                       "options":  [
                                       "What are you going to do about it?",
                                       "What you doing about it?",
                                       "Where you going about it?"
                                   ],
                       "correctAnswerIndex":  0
                   },
                   {
                       "id":  "LIS_FASTSPEECHDECODER_L22_Q1",
                       "interactionType":  "Speed Dial",
                       "xp":  10,
                       "coins":  10,
                       "hint":  "Focus on \u0027Whatcha\u0027 and \u0027gonna\u0027.",
                       "explanation":  "Decoding fast speech improves real-world fluency.",
                       "textToSpeak":  "Whatcha gonna do about it?",
                       "options":  [
                                       "What are you going to do about it?",
                                       "What you doing about it?",
                                       "Where you going about it?"
                                   ],
                       "correctAnswerIndex":  0
                   },
                   {
                       "id":  "LIS_FASTSPEECHDECODER_L22_Q2",
                       "interactionType":  "Speed Dial",
                       "xp":  10,
                       "coins":  10,
                       "hint":  "Focus on \u0027Whatcha\u0027 and \u0027gonna\u0027.",
                       "explanation":  "Decoding fast speech improves real-world fluency.",
                       "textToSpeak":  "Whatcha gonna do about it?",
                       "options":  [
                                       "What are you going to do about it?",
                                       "What you doing about it?",
                                       "Where you going about it?"
                                   ],
                       "correctAnswerIndex":  0
                   },
                   {
                       "id":  "LIS_FASTSPEECHDECODER_L22_Q3",
                       "interactionType":  "Speed Dial",
                       "xp":  10,
                       "coins":  10,
                       "hint":  "Focus on \u0027Whatcha\u0027 and \u0027gonna\u0027.",
                       "explanation":  "Decoding fast speech improves real-world fluency.",
                       "textToSpeak":  "Whatcha gonna do about it?",
                       "options":  [
                                       "What are you going to do about it?",
                                       "What you doing about it?",
                                       "Where you going about it?"
                                   ],
                       "correctAnswerIndex":  0
                   },
                   {
                       "id":  "LIS_FASTSPEECHDECODER_L23_Q1",
                       "interactionType":  "Speed Dial",
                       "xp":  10,
                       "coins":  10,
                       "hint":  "Focus on \u0027Whatcha\u0027 and \u0027gonna\u0027.",
                       "explanation":  "Decoding fast speech improves real-world fluency.",
                       "textToSpeak":  "Whatcha gonna do about it?",
                       "options":  [
                                       "What are you going to do about it?",
                                       "What you doing about it?",
                                       "Where you going about it?"
                                   ],
                       "correctAnswerIndex":  0
                   },
                   {
                       "id":  "LIS_FASTSPEECHDECODER_L23_Q2",
                       "interactionType":  "Speed Dial",
                       "xp":  10,
                       "coins":  10,
                       "hint":  "Focus on \u0027Whatcha\u0027 and \u0027gonna\u0027.",
                       "explanation":  "Decoding fast speech improves real-world fluency.",
                       "textToSpeak":  "Whatcha gonna do about it?",
                       "options":  [
                                       "What are you going to do about it?",
                                       "What you doing about it?",
                                       "Where you going about it?"
                                   ],
                       "correctAnswerIndex":  0
                   },
                   {
                       "id":  "LIS_FASTSPEECHDECODER_L23_Q3",
                       "interactionType":  "Speed Dial",
                       "xp":  10,
                       "coins":  10,
                       "hint":  "Focus on \u0027Whatcha\u0027 and \u0027gonna\u0027.",
                       "explanation":  "Decoding fast speech improves real-world fluency.",
                       "textToSpeak":  "Whatcha gonna do about it?",
                       "options":  [
                                       "What are you going to do about it?",
                                       "What you doing about it?",
                                       "Where you going about it?"
                                   ],
                       "correctAnswerIndex":  0
                   },
                   {
                       "id":  "LIS_FASTSPEECHDECODER_L24_Q1",
                       "interactionType":  "Speed Dial",
                       "xp":  10,
                       "coins":  10,
                       "hint":  "Focus on \u0027Whatcha\u0027 and \u0027gonna\u0027.",
                       "explanation":  "Decoding fast speech improves real-world fluency.",
                       "textToSpeak":  "Whatcha gonna do about it?",
                       "options":  [
                                       "What are you going to do about it?",
                                       "What you doing about it?",
                                       "Where you going about it?"
                                   ],
                       "correctAnswerIndex":  0
                   },
                   {
                       "id":  "LIS_FASTSPEECHDECODER_L24_Q2",
                       "interactionType":  "Speed Dial",
                       "xp":  10,
                       "coins":  10,
                       "hint":  "Focus on \u0027Whatcha\u0027 and \u0027gonna\u0027.",
                       "explanation":  "Decoding fast speech improves real-world fluency.",
                       "textToSpeak":  "Whatcha gonna do about it?",
                       "options":  [
                                       "What are you going to do about it?",
                                       "What you doing about it?",
                                       "Where you going about it?"
                                   ],
                       "correctAnswerIndex":  0
                   },
                   {
                       "id":  "LIS_FASTSPEECHDECODER_L24_Q3",
                       "interactionType":  "Speed Dial",
                       "xp":  10,
                       "coins":  10,
                       "hint":  "Focus on \u0027Whatcha\u0027 and \u0027gonna\u0027.",
                       "explanation":  "Decoding fast speech improves real-world fluency.",
                       "textToSpeak":  "Whatcha gonna do about it?",
                       "options":  [
                                       "What are you going to do about it?",
                                       "What you doing about it?",
                                       "Where you going about it?"
                                   ],
                       "correctAnswerIndex":  0
                   },
                   {
                       "id":  "LIS_FASTSPEECHDECODER_L25_Q1",
                       "interactionType":  "Speed Dial",
                       "xp":  10,
                       "coins":  10,
                       "hint":  "Focus on \u0027Whatcha\u0027 and \u0027gonna\u0027.",
                       "explanation":  "Decoding fast speech improves real-world fluency.",
                       "textToSpeak":  "Whatcha gonna do about it?",
                       "options":  [
                                       "What are you going to do about it?",
                                       "What you doing about it?",
                                       "Where you going about it?"
                                   ],
                       "correctAnswerIndex":  0
                   },
                   {
                       "id":  "LIS_FASTSPEECHDECODER_L25_Q2",
                       "interactionType":  "Speed Dial",
                       "xp":  10,
                       "coins":  10,
                       "hint":  "Focus on \u0027Whatcha\u0027 and \u0027gonna\u0027.",
                       "explanation":  "Decoding fast speech improves real-world fluency.",
                       "textToSpeak":  "Whatcha gonna do about it?",
                       "options":  [
                                       "What are you going to do about it?",
                                       "What you doing about it?",
                                       "Where you going about it?"
                                   ],
                       "correctAnswerIndex":  0
                   },
                   {
                       "id":  "LIS_FASTSPEECHDECODER_L25_Q3",
                       "interactionType":  "Speed Dial",
                       "xp":  10,
                       "coins":  10,
                       "hint":  "Focus on \u0027Whatcha\u0027 and \u0027gonna\u0027.",
                       "explanation":  "Decoding fast speech improves real-world fluency.",
                       "textToSpeak":  "Whatcha gonna do about it?",
                       "options":  [
                                       "What are you going to do about it?",
                                       "What you doing about it?",
                                       "Where you going about it?"
                                   ],
                       "correctAnswerIndex":  0
                   },
                   {
                       "id":  "LIS_FASTSPEECHDECODER_L26_Q1",
                       "interactionType":  "Speed Dial",
                       "xp":  10,
                       "coins":  10,
                       "hint":  "Focus on \u0027Whatcha\u0027 and \u0027gonna\u0027.",
                       "explanation":  "Decoding fast speech improves real-world fluency.",
                       "textToSpeak":  "Whatcha gonna do about it?",
                       "options":  [
                                       "What are you going to do about it?",
                                       "What you doing about it?",
                                       "Where you going about it?"
                                   ],
                       "correctAnswerIndex":  0
                   },
                   {
                       "id":  "LIS_FASTSPEECHDECODER_L26_Q2",
                       "interactionType":  "Speed Dial",
                       "xp":  10,
                       "coins":  10,
                       "hint":  "Focus on \u0027Whatcha\u0027 and \u0027gonna\u0027.",
                       "explanation":  "Decoding fast speech improves real-world fluency.",
                       "textToSpeak":  "Whatcha gonna do about it?",
                       "options":  [
                                       "What are you going to do about it?",
                                       "What you doing about it?",
                                       "Where you going about it?"
                                   ],
                       "correctAnswerIndex":  0
                   },
                   {
                       "id":  "LIS_FASTSPEECHDECODER_L26_Q3",
                       "interactionType":  "Speed Dial",
                       "xp":  10,
                       "coins":  10,
                       "hint":  "Focus on \u0027Whatcha\u0027 and \u0027gonna\u0027.",
                       "explanation":  "Decoding fast speech improves real-world fluency.",
                       "textToSpeak":  "Whatcha gonna do about it?",
                       "options":  [
                                       "What are you going to do about it?",
                                       "What you doing about it?",
                                       "Where you going about it?"
                                   ],
                       "correctAnswerIndex":  0
                   },
                   {
                       "id":  "LIS_FASTSPEECHDECODER_L27_Q1",
                       "interactionType":  "Speed Dial",
                       "xp":  10,
                       "coins":  10,
                       "hint":  "Focus on \u0027Whatcha\u0027 and \u0027gonna\u0027.",
                       "explanation":  "Decoding fast speech improves real-world fluency.",
                       "textToSpeak":  "Whatcha gonna do about it?",
                       "options":  [
                                       "What are you going to do about it?",
                                       "What you doing about it?",
                                       "Where you going about it?"
                                   ],
                       "correctAnswerIndex":  0
                   },
                   {
                       "id":  "LIS_FASTSPEECHDECODER_L27_Q2",
                       "interactionType":  "Speed Dial",
                       "xp":  10,
                       "coins":  10,
                       "hint":  "Focus on \u0027Whatcha\u0027 and \u0027gonna\u0027.",
                       "explanation":  "Decoding fast speech improves real-world fluency.",
                       "textToSpeak":  "Whatcha gonna do about it?",
                       "options":  [
                                       "What are you going to do about it?",
                                       "What you doing about it?",
                                       "Where you going about it?"
                                   ],
                       "correctAnswerIndex":  0
                   },
                   {
                       "id":  "LIS_FASTSPEECHDECODER_L27_Q3",
                       "interactionType":  "Speed Dial",
                       "xp":  10,
                       "coins":  10,
                       "hint":  "Focus on \u0027Whatcha\u0027 and \u0027gonna\u0027.",
                       "explanation":  "Decoding fast speech improves real-world fluency.",
                       "textToSpeak":  "Whatcha gonna do about it?",
                       "options":  [
                                       "What are you going to do about it?",
                                       "What you doing about it?",
                                       "Where you going about it?"
                                   ],
                       "correctAnswerIndex":  0
                   },
                   {
                       "id":  "LIS_FASTSPEECHDECODER_L28_Q1",
                       "interactionType":  "Speed Dial",
                       "xp":  10,
                       "coins":  10,
                       "hint":  "Focus on \u0027Whatcha\u0027 and \u0027gonna\u0027.",
                       "explanation":  "Decoding fast speech improves real-world fluency.",
                       "textToSpeak":  "Whatcha gonna do about it?",
                       "options":  [
                                       "What are you going to do about it?",
                                       "What you doing about it?",
                                       "Where you going about it?"
                                   ],
                       "correctAnswerIndex":  0
                   },
                   {
                       "id":  "LIS_FASTSPEECHDECODER_L28_Q2",
                       "interactionType":  "Speed Dial",
                       "xp":  10,
                       "coins":  10,
                       "hint":  "Focus on \u0027Whatcha\u0027 and \u0027gonna\u0027.",
                       "explanation":  "Decoding fast speech improves real-world fluency.",
                       "textToSpeak":  "Whatcha gonna do about it?",
                       "options":  [
                                       "What are you going to do about it?",
                                       "What you doing about it?",
                                       "Where you going about it?"
                                   ],
                       "correctAnswerIndex":  0
                   },
                   {
                       "id":  "LIS_FASTSPEECHDECODER_L28_Q3",
                       "interactionType":  "Speed Dial",
                       "xp":  10,
                       "coins":  10,
                       "hint":  "Focus on \u0027Whatcha\u0027 and \u0027gonna\u0027.",
                       "explanation":  "Decoding fast speech improves real-world fluency.",
                       "textToSpeak":  "Whatcha gonna do about it?",
                       "options":  [
                                       "What are you going to do about it?",
                                       "What you doing about it?",
                                       "Where you going about it?"
                                   ],
                       "correctAnswerIndex":  0
                   },
                   {
                       "id":  "LIS_FASTSPEECHDECODER_L29_Q1",
                       "interactionType":  "Speed Dial",
                       "xp":  10,
                       "coins":  10,
                       "hint":  "Focus on \u0027Whatcha\u0027 and \u0027gonna\u0027.",
                       "explanation":  "Decoding fast speech improves real-world fluency.",
                       "textToSpeak":  "Whatcha gonna do about it?",
                       "options":  [
                                       "What are you going to do about it?",
                                       "What you doing about it?",
                                       "Where you going about it?"
                                   ],
                       "correctAnswerIndex":  0
                   },
                   {
                       "id":  "LIS_FASTSPEECHDECODER_L29_Q2",
                       "interactionType":  "Speed Dial",
                       "xp":  10,
                       "coins":  10,
                       "hint":  "Focus on \u0027Whatcha\u0027 and \u0027gonna\u0027.",
                       "explanation":  "Decoding fast speech improves real-world fluency.",
                       "textToSpeak":  "Whatcha gonna do about it?",
                       "options":  [
                                       "What are you going to do about it?",
                                       "What you doing about it?",
                                       "Where you going about it?"
                                   ],
                       "correctAnswerIndex":  0
                   },
                   {
                       "id":  "LIS_FASTSPEECHDECODER_L29_Q3",
                       "interactionType":  "Speed Dial",
                       "xp":  10,
                       "coins":  10,
                       "hint":  "Focus on \u0027Whatcha\u0027 and \u0027gonna\u0027.",
                       "explanation":  "Decoding fast speech improves real-world fluency.",
                       "textToSpeak":  "Whatcha gonna do about it?",
                       "options":  [
                                       "What are you going to do about it?",
                                       "What you doing about it?",
                                       "Where you going about it?"
                                   ],
                       "correctAnswerIndex":  0
                   },
                   {
                       "id":  "LIS_FASTSPEECHDECODER_L30_Q1",
                       "interactionType":  "Speed Dial",
                       "xp":  10,
                       "coins":  10,
                       "hint":  "Focus on \u0027Whatcha\u0027 and \u0027gonna\u0027.",
                       "explanation":  "Decoding fast speech improves real-world fluency.",
                       "textToSpeak":  "Whatcha gonna do about it?",
                       "options":  [
                                       "What are you going to do about it?",
                                       "What you doing about it?",
                                       "Where you going about it?"
                                   ],
                       "correctAnswerIndex":  0
                   },
                   {
                       "id":  "LIS_FASTSPEECHDECODER_L30_Q2",
                       "interactionType":  "Speed Dial",
                       "xp":  10,
                       "coins":  10,
                       "hint":  "Focus on \u0027Whatcha\u0027 and \u0027gonna\u0027.",
                       "explanation":  "Decoding fast speech improves real-world fluency.",
                       "textToSpeak":  "Whatcha gonna do about it?",
                       "options":  [
                                       "What are you going to do about it?",
                                       "What you doing about it?",
                                       "Where you going about it?"
                                   ],
                       "correctAnswerIndex":  0
                   },
                   {
                       "id":  "LIS_FASTSPEECHDECODER_L30_Q3",
                       "interactionType":  "Speed Dial",
                       "xp":  10,
                       "coins":  10,
                       "hint":  "Focus on \u0027Whatcha\u0027 and \u0027gonna\u0027.",
                       "explanation":  "Decoding fast speech improves real-world fluency.",
                       "textToSpeak":  "Whatcha gonna do about it?",
                       "options":  [
                                       "What are you going to do about it?",
                                       "What you doing about it?",
                                       "Where you going about it?"
                                   ],
                       "correctAnswerIndex":  0
                   }
               ]
}
