{
    "gameType":  "branchingDialogue",
    "batchIndex":  12,
    "levels":  "111-120",
    "quests":  [
                   {
                       "id":  "RLP_BRANCHINGDIALOGUE_L111_Q1",
                       "interactionType":  "Path Split",
                       "xp":  10,
                       "coins":  10,
                       "hint":  "Cooperation is key.",
                       "explanation":  "Dialogue shapes the story.",
                       "persona":  "Captain Hektor",
                       "scene":  "Location: The Command Bridge",
                       "options":  [
                                       "Request assistance",
                                       "Maintain silence",
                                       "Scan for data"
                                   ],
                       "correctAnswerIndex":  0
                   },
                   {
                       "id":  "RLP_BRANCHINGDIALOGUE_L111_Q2",
                       "interactionType":  "Path Split",
                       "xp":  10,
                       "coins":  10,
                       "hint":  "Cooperation is key.",
                       "explanation":  "Dialogue shapes the story.",
                       "persona":  "Dr. Elara",
                       "scene":  "Location: The Bio-Dome",
                       "options":  [
                                       "Request assistance",
                                       "Maintain silence",
                                       "Scan for data"
                                   ],
                       "correctAnswerIndex":  0
                   },
                   {
                       "id":  "RLP_BRANCHINGDIALOGUE_L111_Q3",
                       "interactionType":  "Path Split",
                       "xp":  10,
                       "coins":  10,
                       "hint":  "Cooperation is key.",
                       "explanation":  "Dialogue shapes the story.",
                       "persona":  "Chef O-Ring",
                       "scene":  "Location: The Lower Foundry",
                       "options":  [
                                       "Request assistance",
                                       "Maintain silence",
                                       "Scan for data"
                                   ],
                       "correctAnswerIndex":  0
                   },
                   {
                       "id":  "RLP_BRANCHINGDIALOGUE_L112_Q1",
                       "interactionType":  "Path Split",
                       "xp":  10,
                       "coins":  10,
                       "hint":  "Cooperation is key.",
                       "explanation":  "Dialogue shapes the story.",
                       "persona":  "Pilot Jax",
                       "scene":  "Location: The Sky-Dock",
                       "options":  [
                                       "Request assistance",
                                       "Maintain silence",
                                       "Scan for data"
                                   ],
                       "correctAnswerIndex":  0
                   },
                   {
                       "id":  "RLP_BRANCHINGDIALOGUE_L112_Q2",
                       "interactionType":  "Path Split",
                       "xp":  10,
                       "coins":  10,
                       "hint":  "Cooperation is key.",
                       "explanation":  "Dialogue shapes the story.",
                       "persona":  "Merchant Kael",
                       "scene":  "Location: The Trade District",
                       "options":  [
                                       "Request assistance",
                                       "Maintain silence",
                                       "Scan for data"
                                   ],
                       "correctAnswerIndex":  0
                   },
                   {
                       "id":  "RLP_BRANCHINGDIALOGUE_L112_Q3",
                       "interactionType":  "Path Split",
                       "xp":  10,
                       "coins":  10,
                       "hint":  "Cooperation is key.",
                       "explanation":  "Dialogue shapes the story.",
                       "persona":  "Agent Nyx",
                       "scene":  "Location: The Med-Bay",
                       "options":  [
                                       "Request assistance",
                                       "Maintain silence",
                                       "Scan for data"
                                   ],
                       "correctAnswerIndex":  0
                   },
                   {
                       "id":  "RLP_BRANCHINGDIALOGUE_L113_Q1",
                       "interactionType":  "Path Split",
                       "xp":  10,
                       "coins":  10,
                       "hint":  "Cooperation is key.",
                       "explanation":  "Dialogue shapes the story.",
                       "persona":  "Captain Hektor",
                       "scene":  "Location: The Command Bridge",
                       "options":  [
                                       "Request assistance",
                                       "Maintain silence",
                                       "Scan for data"
                                   ],
                       "correctAnswerIndex":  0
                   },
                   {
                       "id":  "RLP_BRANCHINGDIALOGUE_L113_Q2",
                       "interactionType":  "Path Split",
                       "xp":  10,
                       "coins":  10,
                       "hint":  "Cooperation is key.",
                       "explanation":  "Dialogue shapes the story.",
                       "persona":  "Dr. Elara",
                       "scene":  "Location: The Bio-Dome",
                       "options":  [
                                       "Request assistance",
                                       "Maintain silence",
                                       "Scan for data"
                                   ],
                       "correctAnswerIndex":  0
                   },
                   {
                       "id":  "RLP_BRANCHINGDIALOGUE_L113_Q3",
                       "interactionType":  "Path Split",
                       "xp":  10,
                       "coins":  10,
                       "hint":  "Cooperation is key.",
                       "explanation":  "Dialogue shapes the story.",
                       "persona":  "Chef O-Ring",
                       "scene":  "Location: The Lower Foundry",
                       "options":  [
                                       "Request assistance",
                                       "Maintain silence",
                                       "Scan for data"
                                   ],
                       "correctAnswerIndex":  0
                   },
                   {
                       "id":  "RLP_BRANCHINGDIALOGUE_L114_Q1",
                       "interactionType":  "Path Split",
                       "xp":  10,
                       "coins":  10,
                       "hint":  "Cooperation is key.",
                       "explanation":  "Dialogue shapes the story.",
                       "persona":  "Pilot Jax",
                       "scene":  "Location: The Sky-Dock",
                       "options":  [
                                       "Request assistance",
                                       "Maintain silence",
                                       "Scan for data"
                                   ],
                       "correctAnswerIndex":  0
                   },
                   {
                       "id":  "RLP_BRANCHINGDIALOGUE_L114_Q2",
                       "interactionType":  "Path Split",
                       "xp":  10,
                       "coins":  10,
                       "hint":  "Cooperation is key.",
                       "explanation":  "Dialogue shapes the story.",
                       "persona":  "Merchant Kael",
                       "scene":  "Location: The Trade District",
                       "options":  [
                                       "Request assistance",
                                       "Maintain silence",
                                       "Scan for data"
                                   ],
                       "correctAnswerIndex":  0
                   },
                   {
                       "id":  "RLP_BRANCHINGDIALOGUE_L114_Q3",
                       "interactionType":  "Path Split",
                       "xp":  10,
                       "coins":  10,
                       "hint":  "Cooperation is key.",
                       "explanation":  "Dialogue shapes the story.",
                       "persona":  "Agent Nyx",
                       "scene":  "Location: The Med-Bay",
                       "options":  [
                                       "Request assistance",
                                       "Maintain silence",
                                       "Scan for data"
                                   ],
                       "correctAnswerIndex":  0
                   },
                   {
                       "id":  "RLP_BRANCHINGDIALOGUE_L115_Q1",
                       "interactionType":  "Path Split",
                       "xp":  10,
                       "coins":  10,
                       "hint":  "Cooperation is key.",
                       "explanation":  "Dialogue shapes the story.",
                       "persona":  "Captain Hektor",
                       "scene":  "Location: The Command Bridge",
                       "options":  [
                                       "Request assistance",
                                       "Maintain silence",
                                       "Scan for data"
                                   ],
                       "correctAnswerIndex":  0
                   },
                   {
                       "id":  "RLP_BRANCHINGDIALOGUE_L115_Q2",
                       "interactionType":  "Path Split",
                       "xp":  10,
                       "coins":  10,
                       "hint":  "Cooperation is key.",
                       "explanation":  "Dialogue shapes the story.",
                       "persona":  "Dr. Elara",
                       "scene":  "Location: The Bio-Dome",
                       "options":  [
                                       "Request assistance",
                                       "Maintain silence",
                                       "Scan for data"
                                   ],
                       "correctAnswerIndex":  0
                   },
                   {
                       "id":  "RLP_BRANCHINGDIALOGUE_L115_Q3",
                       "interactionType":  "Path Split",
                       "xp":  10,
                       "coins":  10,
                       "hint":  "Cooperation is key.",
                       "explanation":  "Dialogue shapes the story.",
                       "persona":  "Chef O-Ring",
                       "scene":  "Location: The Lower Foundry",
                       "options":  [
                                       "Request assistance",
                                       "Maintain silence",
                                       "Scan for data"
                                   ],
                       "correctAnswerIndex":  0
                   },
                   {
                       "id":  "RLP_BRANCHINGDIALOGUE_L116_Q1",
                       "interactionType":  "Path Split",
                       "xp":  10,
                       "coins":  10,
                       "hint":  "Cooperation is key.",
                       "explanation":  "Dialogue shapes the story.",
                       "persona":  "Pilot Jax",
                       "scene":  "Location: The Sky-Dock",
                       "options":  [
                                       "Request assistance",
                                       "Maintain silence",
                                       "Scan for data"
                                   ],
                       "correctAnswerIndex":  0
                   },
                   {
                       "id":  "RLP_BRANCHINGDIALOGUE_L116_Q2",
                       "interactionType":  "Path Split",
                       "xp":  10,
                       "coins":  10,
                       "hint":  "Cooperation is key.",
                       "explanation":  "Dialogue shapes the story.",
                       "persona":  "Merchant Kael",
                       "scene":  "Location: The Trade District",
                       "options":  [
                                       "Request assistance",
                                       "Maintain silence",
                                       "Scan for data"
                                   ],
                       "correctAnswerIndex":  0
                   },
                   {
                       "id":  "RLP_BRANCHINGDIALOGUE_L116_Q3",
                       "interactionType":  "Path Split",
                       "xp":  10,
                       "coins":  10,
                       "hint":  "Cooperation is key.",
                       "explanation":  "Dialogue shapes the story.",
                       "persona":  "Agent Nyx",
                       "scene":  "Location: The Med-Bay",
                       "options":  [
                                       "Request assistance",
                                       "Maintain silence",
                                       "Scan for data"
                                   ],
                       "correctAnswerIndex":  0
                   },
                   {
                       "id":  "RLP_BRANCHINGDIALOGUE_L117_Q1",
                       "interactionType":  "Path Split",
                       "xp":  10,
                       "coins":  10,
                       "hint":  "Cooperation is key.",
                       "explanation":  "Dialogue shapes the story.",
                       "persona":  "Captain Hektor",
                       "scene":  "Location: The Command Bridge",
                       "options":  [
                                       "Request assistance",
                                       "Maintain silence",
                                       "Scan for data"
                                   ],
                       "correctAnswerIndex":  0
                   },
                   {
                       "id":  "RLP_BRANCHINGDIALOGUE_L117_Q2",
                       "interactionType":  "Path Split",
                       "xp":  10,
                       "coins":  10,
                       "hint":  "Cooperation is key.",
                       "explanation":  "Dialogue shapes the story.",
                       "persona":  "Dr. Elara",
                       "scene":  "Location: The Bio-Dome",
                       "options":  [
                                       "Request assistance",
                                       "Maintain silence",
                                       "Scan for data"
                                   ],
                       "correctAnswerIndex":  0
                   },
                   {
                       "id":  "RLP_BRANCHINGDIALOGUE_L117_Q3",
                       "interactionType":  "Path Split",
                       "xp":  10,
                       "coins":  10,
                       "hint":  "Cooperation is key.",
                       "explanation":  "Dialogue shapes the story.",
                       "persona":  "Chef O-Ring",
                       "scene":  "Location: The Lower Foundry",
                       "options":  [
                                       "Request assistance",
                                       "Maintain silence",
                                       "Scan for data"
                                   ],
                       "correctAnswerIndex":  0
                   },
                   {
                       "id":  "RLP_BRANCHINGDIALOGUE_L118_Q1",
                       "interactionType":  "Path Split",
                       "xp":  10,
                       "coins":  10,
                       "hint":  "Cooperation is key.",
                       "explanation":  "Dialogue shapes the story.",
                       "persona":  "Pilot Jax",
                       "scene":  "Location: The Sky-Dock",
                       "options":  [
                                       "Request assistance",
                                       "Maintain silence",
                                       "Scan for data"
                                   ],
                       "correctAnswerIndex":  0
                   },
                   {
                       "id":  "RLP_BRANCHINGDIALOGUE_L118_Q2",
                       "interactionType":  "Path Split",
                       "xp":  10,
                       "coins":  10,
                       "hint":  "Cooperation is key.",
                       "explanation":  "Dialogue shapes the story.",
                       "persona":  "Merchant Kael",
                       "scene":  "Location: The Trade District",
                       "options":  [
                                       "Request assistance",
                                       "Maintain silence",
                                       "Scan for data"
                                   ],
                       "correctAnswerIndex":  0
                   },
                   {
                       "id":  "RLP_BRANCHINGDIALOGUE_L118_Q3",
                       "interactionType":  "Path Split",
                       "xp":  10,
                       "coins":  10,
                       "hint":  "Cooperation is key.",
                       "explanation":  "Dialogue shapes the story.",
                       "persona":  "Agent Nyx",
                       "scene":  "Location: The Med-Bay",
                       "options":  [
                                       "Request assistance",
                                       "Maintain silence",
                                       "Scan for data"
                                   ],
                       "correctAnswerIndex":  0
                   },
                   {
                       "id":  "RLP_BRANCHINGDIALOGUE_L119_Q1",
                       "interactionType":  "Path Split",
                       "xp":  10,
                       "coins":  10,
                       "hint":  "Cooperation is key.",
                       "explanation":  "Dialogue shapes the story.",
                       "persona":  "Captain Hektor",
                       "scene":  "Location: The Command Bridge",
                       "options":  [
                                       "Request assistance",
                                       "Maintain silence",
                                       "Scan for data"
                                   ],
                       "correctAnswerIndex":  0
                   },
                   {
                       "id":  "RLP_BRANCHINGDIALOGUE_L119_Q2",
                       "interactionType":  "Path Split",
                       "xp":  10,
                       "coins":  10,
                       "hint":  "Cooperation is key.",
                       "explanation":  "Dialogue shapes the story.",
                       "persona":  "Dr. Elara",
                       "scene":  "Location: The Bio-Dome",
                       "options":  [
                                       "Request assistance",
                                       "Maintain silence",
                                       "Scan for data"
                                   ],
                       "correctAnswerIndex":  0
                   },
                   {
                       "id":  "RLP_BRANCHINGDIALOGUE_L119_Q3",
                       "interactionType":  "Path Split",
                       "xp":  10,
                       "coins":  10,
                       "hint":  "Cooperation is key.",
                       "explanation":  "Dialogue shapes the story.",
                       "persona":  "Chef O-Ring",
                       "scene":  "Location: The Lower Foundry",
                       "options":  [
                                       "Request assistance",
                                       "Maintain silence",
                                       "Scan for data"
                                   ],
                       "correctAnswerIndex":  0
                   },
                   {
                       "id":  "RLP_BRANCHINGDIALOGUE_L120_Q1",
                       "interactionType":  "Path Split",
                       "xp":  10,
                       "coins":  10,
                       "hint":  "Cooperation is key.",
                       "explanation":  "Dialogue shapes the story.",
                       "persona":  "Pilot Jax",
                       "scene":  "Location: The Sky-Dock",
                       "options":  [
                                       "Request assistance",
                                       "Maintain silence",
                                       "Scan for data"
                                   ],
                       "correctAnswerIndex":  0
                   },
                   {
                       "id":  "RLP_BRANCHINGDIALOGUE_L120_Q2",
                       "interactionType":  "Path Split",
                       "xp":  10,
                       "coins":  10,
                       "hint":  "Cooperation is key.",
                       "explanation":  "Dialogue shapes the story.",
                       "persona":  "Merchant Kael",
                       "scene":  "Location: The Trade District",
                       "options":  [
                                       "Request assistance",
                                       "Maintain silence",
                                       "Scan for data"
                                   ],
                       "correctAnswerIndex":  0
                   },
                   {
                       "id":  "RLP_BRANCHINGDIALOGUE_L120_Q3",
                       "interactionType":  "Path Split",
                       "xp":  10,
                       "coins":  10,
                       "hint":  "Cooperation is key.",
                       "explanation":  "Dialogue shapes the story.",
                       "persona":  "Agent Nyx",
                       "scene":  "Location: The Med-Bay",
                       "options":  [
                                       "Request assistance",
                                       "Maintain silence",
                                       "Scan for data"
                                   ],
                       "correctAnswerIndex":  0
                   }
               ]
}
